vigilant/__init__.py
vigilant/attributes.py
vigilant/config.py
vigilant/instance.py
vigilant/log_batcher.py
vigilant/logs.py
vigilant/message.py
vigilant/metric_batcher.py
vigilant/metrics.py
vigilant/passthrough.py
vigilant/router.py
vigilant/types.py
vigilant/utils.py
vigilant/vigilant.py
vigilant_py-3.1.0.dist-info/METADATA
vigilant_py-3.1.0.dist-info/WHEEL
vigilant_py-3.1.0.dist-info/top_level.txt
vigilant_py-3.1.0.dist-info/RECORD
