Metadata-Version: 2.4
Name: vigilant-py
Version: 3.1.0
Summary: Python SDK for Vigilant (https://vigilant.run)
Home-page: https://vigilant.run
Author: Vigilant Team
Author-email: Vigilant Team <support@vigilant.run>
Requires-Python: >=3.7
Requires-Dist: requests>=2.28.0
Provides-Extra: dev
Requires-Dist: ruff; extra == "dev"
Dynamic: author
Dynamic: home-page
Dynamic: requires-python
